richmin/__init__.py
richmin/admin_mixin.py
richmin/apps.py
richmin/settings.py
richmin/utils.py
richmin/locale/bg/LC_MESSAGES/django.mo
richmin/locale/bg/LC_MESSAGES/django.po
richmin/locale/de/LC_MESSAGES/django.mo
richmin/locale/de/LC_MESSAGES/django.po
richmin/locale/es/LC_MESSAGES/django.mo
richmin/locale/es/LC_MESSAGES/django.po
richmin/locale/fa/LC_MESSAGES/django.mo
richmin/locale/fa/LC_MESSAGES/django.po
richmin/locale/fr/LC_MESSAGES/django.mo
richmin/locale/fr/LC_MESSAGES/django.po
richmin/locale/hu/LC_MESSAGES/django.mo
richmin/locale/hu/LC_MESSAGES/django.po
richmin/locale/ru/LC_MESSAGES/django.mo
richmin/locale/ru/LC_MESSAGES/django.po
richmin/locale/zh_Hans/LC_MESSAGES/django.mo
richmin/locale/zh_Hans/LC_MESSAGES/django.po
richmin/locale/zh_Hant/LC_MESSAGES/django.mo
richmin/locale/zh_Hant/LC_MESSAGES/django.po
richmin/static/admin/js/cancel.js
richmin/static/admin/js/popup_response.js
richmin/static/admin/js/vendor/jquery/jquery.js
richmin/static/admin/js/vendor/jquery/jquery.min.js
richmin/static/richmin/css/bootstrap-rtl.min.css
richmin/static/richmin/css/ltr.css
richmin/static/richmin/css/main.css
richmin/static/richmin/css/rtl.css
richmin/static/richmin/img/calendar-icons.svg
richmin/static/richmin/img/selector-icons.svg
richmin/static/richmin/js/change_form.js
richmin/static/richmin/js/change_list.js
richmin/static/richmin/js/main.js
richmin/static/richmin/js/related-modal.js
richmin/static/richmin/js/ui-builder.js
richmin/static/richmin/plugins/bootstrap-show-modal/bootstrap-show-modal.min.js
richmin/static/vendor/adminlte/css/adminlte.min.css
richmin/static/vendor/adminlte/css/adminlte.min.css.map
richmin/static/vendor/adminlte/img/AdminLTELogo.png
richmin/static/vendor/adminlte/img/icons.png
richmin/static/vendor/adminlte/img/user2-160x160.jpg
richmin/static/vendor/adminlte/js/adminlte.min.js
richmin/static/vendor/adminlte/js/adminlte.min.js.map
richmin/static/vendor/bootstrap/js/bootstrap.min.js
django_richmin-0.2.8.dist-info/METADATA
django_richmin-0.2.8.dist-info/WHEEL
django_richmin-0.2.8.dist-info/top_level.txt
django_richmin-0.2.8.dist-info/RECORD
